setup.py
opal_referral.egg-info/PKG-INFO
opal_referral.egg-info/SOURCES.txt
opal_referral.egg-info/dependency_links.txt
opal_referral.egg-info/pbr.json
opal_referral.egg-info/top_level.txt
referral/__init__.py
referral/api.py
referral/routes.py
referral/urls.py
referral/views.py