Metadata-Version: 1.0
Name: opal-referral
Version: 0.2.1
Summary: OPAL Referral Portal plugin 
Home-page: http://opal.openhealthcare.org.uk/
Author: Open Health Care UK
Author-email: hello@openhealthcare.org.uk
License: GPL3
Platform: UNKNOWN
